procaaso_state_machine/__init__.py
procaaso_state_machine/procaaso_event.py
procaaso_state_machine/procaaso_state.py
procaaso_state_machine/procaaso_state_machine.py
procaaso_state_machine-0.0.3.dist-info/LICENSE
procaaso_state_machine-0.0.3.dist-info/METADATA
procaaso_state_machine-0.0.3.dist-info/WHEEL
procaaso_state_machine-0.0.3.dist-info/RECORD
