Metadata-Version: 2.1
Name: procaaso_state_machine
Version: 0.0.3
Summary: 
Author: Procaaso
Author-email: mdorado@consynsys.com
Requires-Python: >=3.8,<4.0
Classifier: Programming Language :: Python :: 3
Classifier: Programming Language :: Python :: 3.8
Classifier: Programming Language :: Python :: 3.9
Classifier: Programming Language :: Python :: 3.10
Classifier: Programming Language :: Python :: 3.11
Classifier: Programming Language :: Python :: 3.12
Requires-Dist: pydantic (>=1.10.9,<2.0.0)
Requires-Dist: pytest (>=7.0,<8.0)
